{
  "generated_at": "2026-03-08T21:56:29.805552+00:00",
  "source_url": "https://libertyleagueathletics.com/stats.aspx?path=baseball&year=2026",
  "mode": "requests",
  "rows": [
    {
      "team": "Skidmore",
      "index": "",
      "era": "1.29",
      "w-l": "2-0",
      "g": "2",
      "sho": "0",
      "sv": "1",
      "ip": "14.0",
      "h": "5",
      "r": "3",
      "er": "2",
      "bb": "4",
      "so": "24-4",
      "2b": "2",
      "3b": "0",
      "hr": "0",
      "ab": "47",
      "b/avg": ".106",
      "wp": "1",
      "hbp": "3",
      "bk": "0",
      "sfa": "0",
      "sha": "0",
      "wins": 2,
      "losses": 0
    },
    {
      "team": "Hobart",
      "index": "",
      "era": "4.07",
      "w-l": "6-5",
      "g": "11",
      "sho": "1",
      "sv": "2",
      "ip": "79.2",
      "h": "81",
      "r": "44",
      "er": "36",
      "bb": "38",
      "so": "57-24",
      "2b": "14",
      "3b": "4",
      "hr": "2",
      "ab": "301",
      "b/avg": ".269",
      "wp": "4",
      "hbp": "20",
      "bk": "1",
      "sfa": "4",
      "sha": "2",
      "wins": 6,
      "losses": 5
    },
    {
      "team": "RPI",
      "index": "",
      "era": "5.58",
      "w-l": "2-4",
      "g": "6",
      "sho": "0",
      "sv": "1",
      "ip": "50.0",
      "h": "61",
      "r": "40",
      "er": "31",
      "bb": "29",
      "so": "44-9",
      "2b": "15",
      "3b": "2",
      "hr": "1",
      "ab": "206",
      "b/avg": ".296",
      "wp": "6",
      "hbp": "11",
      "bk": "0",
      "sfa": "2",
      "sha": "5",
      "wins": 2,
      "losses": 4
    },
    {
      "team": "Clarkson",
      "index": "",
      "era": "5.85",
      "w-l": "3-2",
      "g": "5",
      "sho": "1",
      "sv": "1",
      "ip": "40.0",
      "h": "41",
      "r": "29",
      "er": "26",
      "bb": "22",
      "so": "30-5",
      "2b": "6",
      "3b": "3",
      "hr": "1",
      "ab": "157",
      "b/avg": ".261",
      "wp": "8",
      "hbp": "6",
      "bk": "0",
      "sfa": "1",
      "sha": "2",
      "wins": 3,
      "losses": 2
    },
    {
      "team": "RIT",
      "index": "",
      "era": "6.18",
      "w-l": "4-5",
      "g": "9",
      "sho": "0",
      "sv": "0",
      "ip": "71.1",
      "h": "63",
      "r": "60",
      "er": "49",
      "bb": "53",
      "so": "78-32",
      "2b": "12",
      "3b": "3",
      "hr": "4",
      "ab": "264",
      "b/avg": ".239",
      "wp": "7",
      "hbp": "24",
      "bk": "0",
      "sfa": "4",
      "sha": "1",
      "wins": 4,
      "losses": 5
    },
    {
      "team": "St. Lawrence",
      "index": "",
      "era": "6.48",
      "w-l": "4-3",
      "g": "7",
      "sho": "1",
      "sv": "2",
      "ip": "50.0",
      "h": "59",
      "r": "41",
      "er": "36",
      "bb": "31",
      "so": "41-8",
      "2b": "13",
      "3b": "1",
      "hr": "1",
      "ab": "196",
      "b/avg": ".301",
      "wp": "6",
      "hbp": "10",
      "bk": "2",
      "sfa": "2",
      "sha": "4",
      "wins": 4,
      "losses": 3
    },
    {
      "team": "Union",
      "index": "",
      "era": "6.84",
      "w-l": "2-1",
      "g": "3",
      "sho": "0",
      "sv": "0",
      "ip": "25.0",
      "h": "22",
      "r": "20",
      "er": "19",
      "bb": "18",
      "so": "14-6",
      "2b": "6",
      "3b": "0",
      "hr": "2",
      "ab": "86",
      "b/avg": ".256",
      "wp": "2",
      "hbp": "7",
      "bk": "0",
      "sfa": "3",
      "sha": "2",
      "wins": 2,
      "losses": 1
    },
    {
      "team": "Rochester",
      "index": "",
      "era": "8.61",
      "w-l": "3-0",
      "g": "3",
      "sho": "0",
      "sv": "1",
      "ip": "23.0",
      "h": "33",
      "r": "22",
      "er": "22",
      "bb": "12",
      "so": "20-6",
      "2b": "4",
      "3b": "2",
      "hr": "3",
      "ab": "95",
      "b/avg": ".347",
      "wp": "1",
      "hbp": "7",
      "bk": "2",
      "sfa": "2",
      "sha": "0",
      "wins": 3,
      "losses": 0
    },
    {
      "team": "Ithaca",
      "index": "",
      "era": "8.69",
      "w-l": "3-2",
      "g": "5",
      "sho": "0",
      "sv": "1",
      "ip": "39.1",
      "h": "48",
      "r": "53",
      "er": "38",
      "bb": "42",
      "so": "41-16",
      "2b": "12",
      "3b": "2",
      "hr": "1",
      "ab": "167",
      "b/avg": ".287",
      "wp": "7",
      "hbp": "16",
      "bk": "3",
      "sfa": "0",
      "sha": "1",
      "wins": 3,
      "losses": 2
    },
    {
      "team": "Vassar",
      "index": "",
      "era": "9.00",
      "w-l": "0-2",
      "g": "2",
      "sho": "0",
      "sv": "0",
      "ip": "13.0",
      "h": "12",
      "r": "15",
      "er": "13",
      "bb": "15",
      "so": "14-6",
      "2b": "2",
      "3b": "1",
      "hr": "0",
      "ab": "52",
      "b/avg": ".231",
      "wp": "3",
      "hbp": "6",
      "bk": "0",
      "sfa": "1",
      "sha": "0",
      "wins": 0,
      "losses": 2
    },
    {
      "team": "Bard",
      "index": "",
      "era": "10.50",
      "w-l": "2-2",
      "g": "4",
      "sho": "1",
      "sv": "1",
      "ip": "30.0",
      "h": "37",
      "r": "38",
      "er": "35",
      "bb": "23",
      "so": "41-12",
      "2b": "9",
      "3b": "2",
      "hr": "5",
      "ab": "130",
      "b/avg": ".285",
      "wp": "10",
      "hbp": "14",
      "bk": "0",
      "sfa": "1",
      "sha": "1",
      "wins": 2,
      "losses": 2
    }
  ],
  "error": null
}